pandas_extras/__init__.py
pandas_extras/conversions.py
pandas_extras/hierarchy.py
pandas_extras/transformations.py
pandas_extras/util.py
pandas_extras-0.0.6.dist-info/LICENSE
pandas_extras-0.0.6.dist-info/METADATA
pandas_extras-0.0.6.dist-info/WHEEL
pandas_extras-0.0.6.dist-info/top_level.txt
pandas_extras-0.0.6.dist-info/RECORD
