Metadata-Version: 2.1
Name: pandas-extras
Version: 0.0.6
Summary: Extension package for the popular Pandas library
Home-page: https://github.com/nokia/pandas-extras
Maintainer: Hodossy, Szabolcs
Maintainer-email: hodossy.szabolcs@gmail.com
License: BSD
Keywords: pandas,data analysis,data transformation
Platform: any
Classifier: Development Status :: 5 - Production/Stable
Classifier: Environment :: Console
Classifier: Operating System :: OS Independent
Classifier: Intended Audience :: Science/Research
Classifier: Topic :: Scientific/Engineering
Classifier: Programming Language :: Python
Classifier: Programming Language :: Python :: 3
Classifier: Programming Language :: Python :: 3.6
Classifier: Programming Language :: Python :: 3.7
Classifier: Programming Language :: Python :: 3.8
Classifier: Programming Language :: Python :: 3.9
Requires-Python: >=3.6
Requires-Dist: pandas
